Metadata-Version: 2.1
Name: pycourseexam
Version: 0.0.1
Summary: Módulo para determinar alumnos que aprobaron el curso, dependiendo la secuencia de examenes (parcial, recuperatorio), la cantidad de examenes, y las notas para aprobarlos.
Home-page: UNKNOWN
Author: @Mato
Author-email: no@email.org
License: MIT
Keywords: student,course management,course,university
Platform: UNKNOWN
Classifier: Development Status :: 1 - Planning
Classifier: Intended Audience :: Education
Classifier: Operating System :: POSIX :: Linux
Classifier: License :: OSI Approved :: MIT License
Classifier: Programming Language :: Python :: 3
